[{"_path":"/scripts/gui/gui_components","_dir":"gui","_draft":false,"_partial":false,"_locale":"","title":"Gui components","description":"","_type":"markdown","_id":"content:2.Scripts:1.gui:2.gui_components.md","_source":"content","_file":"2.Scripts/1.gui/2.gui_components.md","_extension":"md"},{"_path":"/table/setup","_dir":"table","_draft":false,"_partial":false,"_locale":"","title":"Setup","description":"","_type":"markdown","_id":"content:2.Table:0.setup.md","_source":"content","_file":"2.Table/0.setup.md","_extension":"md"}]